{"last_node_id":37,"last_link_id":71,"nodes":[{"id":7,"type":"VAEDecode","pos":[1756.1666259765625,133.80718994140625],"size":[210,46],"flags":{},"order":10,"mode":0,"inputs":[{"name":"samples","type":"LATENT","link":9,"label":"Latent"},{"name":"vae","type":"VAE","link":22,"label":"VAE"}],"outputs":[{"name":"IMAGE","type":"IMAGE","links":[8],"shape":3,"label":"图像"}],"properties":{"Node name for S&R":"VAEDecode"},"widgets_values":[]},{"id":1,"type":"CheckpointLoaderSimple","pos":[144.5635223388672,53.85050964355469],"size":[315,98],"flags":{},"order":0,"mode":0,"inputs":[],"outputs":[{"name":"MODEL","type":"MODEL","links":[57],"slot_index":0,"shape":3,"label":"模型"},{"name":"CLIP","type":"CLIP","links":[40],"slot_index":1,"shape":3,"label":"CLIP"},{"name":"VAE","type":"VAE","links":[22],"slot_index":2,"shape":3,"label":"VAE"}],"properties":{"Node name for S&R":"CheckpointLoaderSimple"},"widgets_values":["catTowerNoobaiXL_v11EpsilonPred.safetensors"]},{"id":32,"type":"LoraLoader","pos":[504.0139465332031,50.27810287475586],"size":[315,126],"flags":{},"order":2,"mode":0,"inputs":[{"name":"model","type":"MODEL","link":57,"label":"模型"},{"name":"clip","type":"CLIP","link":40,"label":"CLIP"}],"outputs":[{"name":"MODEL","type":"MODEL","links":[65],"slot_index":0,"label":"模型"},{"name":"CLIP","type":"CLIP","links":[64],"slot_index":1,"label":"CLIP"}],"properties":{"Node name for S&R":"LoraLoader"},"widgets_values":["bikabaka.safetensors",0.7000000000000001,1]},{"id":9,"type":"SaveImage","pos":[1751.5831298828125,246.4864044189453],"size":[315,270],"flags":{},"order":11,"mode":0,"inputs":[{"name":"images","type":"IMAGE","link":8,"label":"图像"}],"outputs":[],"properties":{"Node name for S&R":"SaveImage"},"widgets_values":["ComfyUI"]},{"id":36,"type":"LoraLoader","pos":[171.8946533203125,200.34280395507812],"size":[315,126],"flags":{},"order":3,"mode":0,"inputs":[{"name":"model","type":"MODEL","link":65,"label":"模型"},{"name":"clip","type":"CLIP","link":64,"label":"CLIP"}],"outputs":[{"name":"MODEL","type":"MODEL","links":[68],"slot_index":0,"label":"模型"},{"name":"CLIP","type":"CLIP","links":[69],"slot_index":1,"label":"CLIP"}],"properties":{"Node name for S&R":"LoraLoader"},"widgets_values":["hand 4.safetensors",0.7000000000000001,1]},{"id":37,"type":"LoraLoader","pos":[166.15933227539062,379.32818603515625],"size":[315,126],"flags":{},"order":4,"mode":0,"inputs":[{"name":"model","type":"MODEL","link":68,"label":"模型"},{"name":"clip","type":"CLIP","link":69,"label":"CLIP"}],"outputs":[{"name":"MODEL","type":"MODEL","links":[71],"label":"模型","slot_index":0},{"name":"CLIP","type":"CLIP","links":[70],"label":"CLIP","slot_index":1}],"properties":{"Node name for S&R":"LoraLoader"},"widgets_values":["Blushing.safetensors",0.7000000000000001,1]},{"id":35,"type":"LoraLoader","pos":[188.6638946533203,551.1421508789062],"size":[315,126],"flags":{},"order":5,"mode":0,"inputs":[{"name":"model","type":"MODEL","link":71,"label":"模型"},{"name":"clip","type":"CLIP","link":70,"label":"CLIP"}],"outputs":[{"name":"MODEL","type":"MODEL","links":[60],"slot_index":0,"label":"模型"},{"name":"CLIP","type":"CLIP","links":[61],"slot_index":1,"label":"CLIP"}],"properties":{"Node name for S&R":"LoraLoader"},"widgets_values":["CottonTights-IL.safetensors",0.6,1]},{"id":5,"type":"KSampler","pos":[1392.950927734375,145.9232635498047],"size":[315,474],"flags":{},"order":9,"mode":0,"inputs":[{"name":"model","type":"MODEL","link":62,"label":"模型"},{"name":"positive","type":"CONDITIONING","link":36,"label":"正面条件"},{"name":"negative","type":"CONDITIONING","link":37,"label":"负面条件"},{"name":"latent_image","type":"LATENT","link":7,"label":"Latent"}],"outputs":[{"name":"LATENT","type":"LATENT","links":[9],"shape":3,"label":"Latent"}],"properties":{"Node name for S&R":"KSampler"},"widgets_values":[653459313408805,"randomize",30,7,"euler_ancestral","normal",1]},{"id":33,"type":"LoraLoader","pos":[537.9616088867188,243.92417907714844],"size":[315,126],"flags":{},"order":6,"mode":0,"inputs":[{"name":"model","type":"MODEL","link":60,"label":"模型"},{"name":"clip","type":"CLIP","link":61,"label":"CLIP"}],"outputs":[{"name":"MODEL","type":"MODEL","links":[62],"slot_index":0,"label":"模型"},{"name":"CLIP","type":"CLIP","links":[49,63],"slot_index":1,"label":"CLIP"}],"properties":{"Node name for S&R":"LoraLoader"},"widgets_values":["add-detail-xl.safetensors",3,1]},{"id":28,"type":"CLIPTextEncode","pos":[934.9341430664062,86.09904479980469],"size":[400,200],"flags":{},"order":8,"mode":0,"inputs":[{"name":"clip","type":"CLIP","link":63,"label":"CLIP"}],"outputs":[{"name":"CONDITIONING","type":"CONDITIONING","links":[36],"slot_index":0,"label":"条件"}],"properties":{"Node name for S&R":"CLIPTextEncode"},"widgets_values":["masterpiece, best quality,HDR,UHD,8K,three_girls,sailor_shirt,cat_ears,big breasts,long hair,blunt bangs,full body,shiny skin,cute face,Blue eyes,blonde hair,mini skirt,(cat_tail:1.1),tactical headset,night_sky,Slightly open mouth,no_shoes,paw pose,lifting one leg,submachine gun,(black_cotton_tights:1.5), <lora:bikabaka:[STR]>,tianliang_duohe_fangdongye:[STR],"]},{"id":6,"type":"EmptyLatentImage","pos":[593.984619140625,446.09912109375],"size":[315,106],"flags":{},"order":1,"mode":0,"inputs":[],"outputs":[{"name":"LATENT","type":"LATENT","links":[7],"shape":3,"label":"Latent"}],"properties":{"Node name for S&R":"EmptyLatentImage"},"widgets_values":[832,1216,3]},{"id":29,"type":"CLIPTextEncode","pos":[947.41552734375,372.4800720214844],"size":[400,200],"flags":{},"order":7,"mode":0,"inputs":[{"name":"clip","type":"CLIP","link":49,"label":"CLIP"}],"outputs":[{"name":"CONDITIONING","type":"CONDITIONING","links":[37],"slot_index":0,"label":"条件"}],"properties":{"Node name for S&R":"CLIPTextEncode"},"widgets_values":["(nsfw:1.05), worst quality, old, early, low quality, lowres, signature, username, logo, bad hands, mutated hands, mammal, anthro, furry, ambiguous form, feral, semi-anthro, embedding:aidxlv05_neg, (halo:1.4), cleavage, r18, (incorrect proportions:1.1),extra toes,deformed eyes,"]}],"links":[[7,6,0,5,3,"LATENT"],[8,7,0,9,0,"IMAGE"],[9,5,0,7,0,"LATENT"],[22,1,2,7,1,"VAE"],[36,28,0,5,1,"CONDITIONING"],[37,29,0,5,2,"CONDITIONING"],[40,1,1,32,1,"CLIP"],[49,33,1,29,0,"CLIP"],[57,1,0,32,0,"MODEL"],[60,35,0,33,0,"MODEL"],[61,35,1,33,1,"CLIP"],[62,33,0,5,0,"MODEL"],[63,33,1,28,0,"CLIP"],[64,32,1,36,1,"CLIP"],[65,32,0,36,0,"MODEL"],[68,36,0,37,0,"MODEL"],[69,36,1,37,1,"CLIP"],[70,37,1,35,1,"CLIP"],[71,37,0,35,0,"MODEL"]],"groups":[],"config":{},"extra":{"ds":{"scale":1.015255979947711,"offset":[-441.07045707280474,38.3859799912662]},"ue_links":[]},"version":0.4}